cfb_predictor/__init__.py
cfb_predictor/cfg.py
cfb_predictor/data_fxns.py
cfb_predictor/data_scrape.py
cfb_predictor/model_testing.py
cfb_predictor/model_training.py
cfb_predictor/neural_network.py
cfb_predictor/train_fxns.py
cfb_predictor-0.2.2.dist-info/METADATA
cfb_predictor-0.2.2.dist-info/WHEEL
cfb_predictor-0.2.2.dist-info/top_level.txt
cfb_predictor-0.2.2.dist-info/RECORD
