Metadata-Version: 2.1
Name: cfb-predictor
Version: 0.2.2
Summary: Rates college football teams
Home-page: https://github.com/sbischof/cfb_predictor
Author: Steven Bischoff
Author-email: steven.m.bischoff@gmail.com
License: UNKNOWN
Platform: UNKNOWN
Classifier: Programming Language :: Python :: 3
Classifier: License :: OSI Approved :: MIT License
Classifier: Operating System :: OS Independent
Requires-Dist: pandas
Requires-Dist: numpy
